[{"model": "admin.logentry", "pk": 1, "fields": {"action_time": "2024-11-15T16:02:50.118Z", "user": 1, "content_type": 14, "object_id": "1", "object_repr": "can be valuers", "action_flag": 1, "change_message": "[{\"added\": {}}]"}}, {"model": "admin.logentry", "pk": 2, "fields": {"action_time": "2024-11-15T16:03:10.314Z", "user": 1, "content_type": 14, "object_id": "2", "object_repr": "can be supervisor", "action_flag": 1, "change_message": "[{\"added\": {}}]"}}, {"model": "admin.logentry", "pk": 3, "fields": {"action_time": "2024-11-15T16:06:58.458Z", "user": 1, "content_type": 14, "object_id": "3", "object_repr": "can perform admin functions", "action_flag": 1, "change_message": "[{\"added\": {}}]"}}, {"model": "admin.logentry", "pk": 4, "fields": {"action_time": "2024-11-15T16:07:11.495Z", "user": 1, "content_type": 14, "object_id": "4", "object_repr": "Can Verify payment as Valuer", "action_flag": 1, "change_message": "[{\"added\": {}}]"}}, {"model": "admin.logentry", "pk": 5, "fields": {"action_time": "2024-11-15T16:07:29.182Z", "user": 1, "content_type": 14, "object_id": "5", "object_repr": "Can View Valuation Requests", "action_flag": 1, "change_message": "[{\"added\": {}}]"}}, {"model": "admin.logentry", "pk": 6, "fields": {"action_time": "2024-11-15T16:07:58.244Z", "user": 1, "content_type": 13, "object_id": "1", "object_repr": "BIK AND BOS", "action_flag": 1, "change_message": "[{\"added\": {}}]"}}, {"model": "admin.logentry", "pk": 7, "fields": {"action_time": "2024-11-15T16:08:17.811Z", "user": 1, "content_type": 15, "object_id": "1", "object_repr": "bik", "action_flag": 2, "change_message": "[{\"changed\": {\"fields\": [\"Companies\", \"Active company\"]}}]"}}, {"model": "admin.logentry", "pk": 8, "fields": {"action_time": "2024-11-15T16:10:03.516Z", "user": 1, "content_type": 14, "object_id": "6", "object_repr": "can view loan origination", "action_flag": 1, "change_message": "[{\"added\": {}}]"}}, {"model": "admin.logentry", "pk": 9, "fields": {"action_time": "2024-11-15T16:11:50.307Z", "user": 1, "content_type": 14, "object_id": "7", "object_repr": "can complete asset valuation detail", "action_flag": 1, "change_message": "[{\"added\": {}}]"}}, {"model": "admin.logentry", "pk": 10, "fields": {"action_time": "2024-11-15T16:12:00.457Z", "user": 1, "content_type": 18, "object_id": "1", "object_repr": "ADMIN - BIK AND BOS", "action_flag": 2, "change_message": "[{\"changed\": {\"fields\": [\"Permissions\"]}}]"}}, {"model": "admin.logentry", "pk": 11, "fields": {"action_time": "2024-11-15T16:19:05.423Z", "user": 1, "content_type": 8, "object_id": "1", "object_repr": "UBK 553G", "action_flag": 3, "change_message": ""}}, {"model": "admin.logentry", "pk": 12, "fields": {"action_time": "2024-11-15T16:25:32.089Z", "user": 1, "content_type": 12, "object_id": "1", "object_repr": "Mercy Aliko", "action_flag": 3, "change_message": ""}}, {"model": "sessions.session", "pk": "l7f7po9vor5whmr2bwvojxjfj6yeug0t", "fields": {"session_data": ".eJxVjMsOwiAURP-FtSG8iuDSvd9ALpeLVA0kpV0Z_12adKG7yZwz82YBtrWErdMS5sQuTLLTbxcBn1R3kB5Q741jq-syR74r_KCd31qi1_Vw_w4K9DLWzgBG4QSSASXkiAgeVNJCo0Gb8yQHNZOO1jqSOquzU1Z68jkbC8A-X9y-N48:1tByyn:CnAjf1ZYKmObNw0V7Srp5ZQBSyRYYLP621DcjE4TcDM", "expire_date": "2024-11-29T16:15:29.121Z"}}, {"model": "sessions.session", "pk": "ugyqrzrovl96k8os2qqjc0k23uecqawm", "fields": {"session_data": ".eJxVjMsOwiAURP-FtSG8iuDSvd9ALpeLVA0kpV0Z_12adKG7yZwz82YBtrWErdMS5sQuTLLTbxcBn1R3kB5Q741jq-syR74r_KCd31qi1_Vw_w4K9DLWzgBG4QSSASXkiAgeVNJCo0Gb8yQHNZOO1jqSOquzU1Z68jkbC8A-X9y-N48:1tBym0:1WdO3HjG61i9uQuM7BdnFamOHzGMB1wiwXWT6QZVLTQ", "expire_date": "2024-11-29T16:02:16.969Z"}}]